wondoner/plugin_github/__init__.py
wondoner/plugin_github/client.py
wondoner/plugin_github/mapping.py
wondoner/plugin_github/plugin.py
wondoner_plugin_github-0.1.2.dist-info/LICENSE
wondoner_plugin_github-0.1.2.dist-info/METADATA
wondoner_plugin_github-0.1.2.dist-info/WHEEL
wondoner_plugin_github-0.1.2.dist-info/entry_points.txt
wondoner_plugin_github-0.1.2.dist-info/RECORD
