Metadata-Version: 2.3
Name: wondoner-plugin-github
Version: 0.1.2
Summary: Wondoner plugin for GitHub integration.
License: MIT
Author: Your Name
Author-email: you@example.com
Requires-Python: >=3.11,<4.0
Classifier: License :: OSI Approved :: MIT License
Classifier: Programming Language :: Python :: 3
Classifier: Programming Language :: Python :: 3.11
Classifier: Programming Language :: Python :: 3.12
Classifier: Programming Language :: Python :: 3.13
Requires-Dist: h11 (>=0.16.0,<0.17.0)
Requires-Dist: httpcore (>=1.0.9,<2.0.0)
Requires-Dist: httpx (>=0.25.0)
Requires-Dist: pipdeptree (>=2.26.1,<3.0.0)
Requires-Dist: wondoner-interfaces (>=0.1.5)
